pingxiwanggit-0.0.2.dist-info/licenses/LICENSE
pingxiwanggitlab/Gitlab.py
pingxiwanggitlab/__init__.py
pingxiwanggit-0.0.2.dist-info/METADATA
pingxiwanggit-0.0.2.dist-info/WHEEL
pingxiwanggit-0.0.2.dist-info/top_level.txt
pingxiwanggit-0.0.2.dist-info/RECORD
