Metadata-Version: 2.4
Name: pingxiwanggit
Version: 0.0.2
Summary: encapsulate simple operations to gitlab
Author-email: pingxiwang <pingxiwang@gmail.com>
License-Expression: MIT
Project-URL: Homepage, https://github.com/pypa/sampleproject
Project-URL: Issues, https://github.com/pypa/sampleproject/issues
Classifier: Programming Language :: Python :: 3
Classifier: Operating System :: OS Independent
Requires-Python: >=3.9
License-File: LICENSE
Dynamic: license-file
